sequential circuits/counters/downcount3bit.v
module downcount3bit (input clk,rst,output reg [2:0] count);
always @(posedge clk or negedge rst)
begin
if(~rst)		//active low reset
count<=3'd7;
else
count<=count-1;
end
endmodule

sequential circuits/counters/downcount3bit_tb.v
module downcount3bit_tb;
reg clk,rst;
wire [2:0] count;
downcount3bit DUT(.clk(clk),.rst(rst),.count(count));
initial 
begin
clk=0;
end
always #2 clk=~clk;
initial
begin
rst=0;#10;
rst=1;#30;
rst=0;#10;
rst=1;#10;
rst=0;#10;
rst=1;#30;
rst=0;#10;
rst=1;
$finish;
end
initial
begin
$dumpfile("downcount3bit.vcd");
$dumpvars(0,downcount3bit_tb);
end
endmodule

sequential circuits/counters/downcount3bit.vcd
$date
	Tue Sep 23 17:34:10 2025
$end
$version
	Icarus Verilog
$end
$timescale
	1s
$end
$scope module downcount3bit_tb $end
$var wire 3 ! count [2:0] $end
$var reg 1 " clk $end
$var reg 1 # rst $end
$scope module DUT $end
$var wire 1 " clk $end
$var wire 1 # rst $end
$var reg 3 $ count [2:0] $end
$upscope $end
$upscope $end
$enddefinitions $end
$comment Show the parameter values. $end
$dumpall
$end
#0
$dumpvars
b111 $
0#
0"
b111 !
$end
#2
1"
#4
0"
#6
1"
#8
0"
#10
b110 !
b110 $
1"
1#
#12
0"
#14
b101 !
b101 $
1"
#16
0"
#18
b100 !
b100 $
1"
#20
0"
#22
b11 !
b11 $
1"
#24
0"
#26
b10 !
b10 $
1"
#28
0"
#30
b1 !
b1 $
1"
#32
0"
#34
b0 !
b0 $
1"
#36
0"
#38
b111 !
b111 $
1"
#40
0"
0#
#42
1"
#44
0"
#46
1"
#48
0"
#50
b110 !
b110 $
1"
1#
#52
0"
#54
b101 !
b101 $
1"
#56
0"
#58
b100 !
b100 $
1"
#60
b111 !
b111 $
0"
0#
#62
1"
#64
0"
#66
1"
#68
0"
#70
b110 !
b110 $
1"
1#
#72
0"
#74
b101 !
b101 $
1"
#76
0"
#78
b100 !
b100 $
1"
#80
0"
#82
b11 !
b11 $
1"
#84
0"
#86
b10 !
b10 $
1"
#88
0"
#90
b1 !
b1 $
1"
#92
0"
#94
b0 !
b0 $
1"
#96
0"
#98
b111 !
b111 $
1"
#100
0"
0#
#102
1"
#104
0"
#106
1"
#108
0"
#110
b110 !
b110 $
1"
1#
