sequential circuits/counters/downcount4bit.v
module downcount4bit (input clk,rst,output reg [3:0]count);
always @(posedge clk or negedge rst)
begin
if(~rst)		//active low reset
count<=4'hf;
else
count<=count-1;
end
endmodule

sequential circuits/counters/downcount4bit_tb.v
module downcount4bit_tb;
reg clk,rst;
wire [3:0]count;
downcount4bit DUT (.clk(clk),.rst(rst),.count(count));
initial
begin
clk=0;
end
always #2 clk=~clk;		//250MHz clock
initial
begin
rst=0;#10;
rst=1;#70;
$finish;
end
initial
begin
$dumpfile("downcount4bit.vcd");
$dumpvars(0,downcount4bit_tb);
end
endmodule

sequential circuits/counters/downcount4bit.vcd
$date
	Tue Sep 23 17:45:15 2025
$end
$version
	Icarus Verilog
$end
$timescale
	1s
$end
$scope module downcount4bit_tb $end
$var wire 4 ! count [3:0] $end
$var reg 1 " clk $end
$var reg 1 # rst $end
$scope module DUT $end
$var wire 1 " clk $end
$var wire 1 # rst $end
$var reg 4 $ count [3:0] $end
$upscope $end
$upscope $end
$enddefinitions $end
$comment Show the parameter values. $end
$dumpall
$end
#0
$dumpvars
b1111 $
0#
0"
b1111 !
$end
#2
1"
#4
0"
#6
1"
#8
0"
#10
b1110 !
b1110 $
1"
1#
#12
0"
#14
b1101 !
b1101 $
1"
#16
0"
#18
b1100 !
b1100 $
1"
#20
0"
#22
b1011 !
b1011 $
1"
#24
0"
#26
b1010 !
b1010 $
1"
#28
0"
#30
b1001 !
b1001 $
1"
#32
0"
#34
b1000 !
b1000 $
1"
#36
0"
#38
b111 !
b111 $
1"
#40
0"
#42
b110 !
b110 $
1"
#44
0"
#46
b101 !
b101 $
1"
#48
0"
#50
b100 !
b100 $
1"
#52
0"
#54
b11 !
b11 $
1"
#56
0"
#58
b10 !
b10 $
1"
#60
0"
#62
b1 !
b1 $
1"
#64
0"
#66
b0 !
b0 $
1"
#68
0"
#70
b1111 !
b1111 $
1"
#72
0"
#74
b1110 !
b1110 $
1"
#76
0"
#78
b1101 !
b1101 $
1"
