sequential circuits/counters/updown3bit.v
module updown3bit(input clk,rst,updown,output reg [2:0] count);
always @(posedge clk or negedge rst)
begin
if(~rst)
count<=0;
else
if(~updown)				//when updown=0 up counting and when updown=1 downcounting
count<=count+1;
else
count<=count-1;
end
endmodule

sequential circuits/counters/updown3bit_tb.v
module updown3bit_tb;
reg clk,rst,updown;
wire [2:0]count;
updown3bit DUT(.clk(clk),.rst(rst),.updown(updown),.count(count));
initial
begin
clk=0;
end
always #2 clk=~clk;
initial
begin
updown=0;
rst=0;#10;
rst=1;#40;
updown=1;
rst=0;#10;
rst=1;#36;
$finish;
end
initial
begin
$dumpfile("updown3bit.vcd");
$dumpvars(0,updown3bit_tb);
end
endmodule

sequential circuits/counters/updown3bit.vcd
$date
	Tue Sep 23 19:24:21 2025
$end
$version
	Icarus Verilog
$end
$timescale
	1s
$end
$scope module updown3bit_tb $end
$var wire 3 ! count [2:0] $end
$var reg 1 " clk $end
$var reg 1 # rst $end
$var reg 1 $ updown $end
$scope module DUT $end
$var wire 1 " clk $end
$var wire 1 # rst $end
$var wire 1 $ updown $end
$var reg 3 % count [2:0] $end
$upscope $end
$upscope $end
$enddefinitions $end
$comment Show the parameter values. $end
$dumpall
$end
#0
$dumpvars
b0 %
0$
0#
0"
b0 !
$end
#2
1"
#4
0"
#6
1"
#8
0"
#10
b1 !
b1 %
1"
1#
#12
0"
#14
b10 !
b10 %
1"
#16
0"
#18
b11 !
b11 %
1"
#20
0"
#22
b100 !
b100 %
1"
#24
0"
#26
b101 !
b101 %
1"
#28
0"
#30
b110 !
b110 %
1"
#32
0"
#34
b111 !
b111 %
1"
#36
0"
#38
b0 !
b0 %
1"
#40
0"
#42
b1 !
b1 %
1"
#44
0"
#46
b10 !
b10 %
1"
#48
0"
#50
b0 !
b0 %
1"
0#
1$
#52
0"
#54
1"
#56
0"
#58
1"
#60
0"
1#
#62
b111 !
b111 %
1"
#64
0"
#66
b110 !
b110 %
1"
#68
0"
#70
b101 !
b101 %
1"
#72
0"
#74
b100 !
b100 %
1"
#76
0"
#78
b11 !
b11 %
1"
#80
0"
#82
b10 !
b10 %
1"
#84
0"
#86
b1 !
b1 %
1"
#88
0"
#90
b0 !
b0 %
1"
#92
0"
#94
b111 !
b111 %
1"
