Comb/Encoder/priority_enc.v
module priority_enc(input [7:0]I , output reg [2:0] out);
always @(*)
begin
if(I[7]==1) begin
out=3'b111;
end
else if(I[6]==1) begin
out=3'b110;
end
else if(I[5]==1) begin
out=3'b101;
end
else if(I[4]==1) begin
out=3'b100;
end
else if(I[3]==1) begin
out=3'b011;
end
else if(I[2]==1) begin
out=3'b010;
end
else if(I[1]==1) begin
out=3'b001;
end
else if(I[0]==1) begin
out=3'b000;
end
else begin
out=3'bxxx;
end
end
endmodule

Comb/Encoder/priority_enc_tb.v
module priority_enc_tb;
reg [7:0]I;
wire [2:0]out;
priority_enc DUT(.I(I),.out(out));
initial
begin
I=8'b00000001;#10;
$display("The output is %d",out);
I=8'b00000011;#10;
$display("The output is %d",out);
I=8'b00000111;#10;
$display("The output is %d",out);
I=8'b00001111;#10;
$display("The output is %d",out);
I=8'b00011111;#10;
$display("The output is %d",out);
I=8'b00111111;#10;
$display("The output is %d",out);
I=8'b01111111;#10;
$display("The output is %d",out);
I=8'b11111111;#10;
$display("The output is %d",out);
I=8'b01011011;#10;
$display("The output is %d",out);
I=8'b11011011;#10;
$display("The output is %d",out);
I=8'b00011011;#10;
$display("The output is %d",out);
I=8'b0011111;#10;
$display("The output is %d",out);
end
initial
begin
$dumpfile("priority_enc.vcd");
$dumpvars(0,priority_enc_tb);
end
endmodule

Comb/Encoder/priority_enc.vcd
$date
	Sun Sep 21 17:25:19 2025
$end
$version
	Icarus Verilog
$end
$timescale
	1s
$end
$scope module priority_enc_tb $end
$var wire 3 ! out [2:0] $end
$var reg 8 " I [7:0] $end
$scope module DUT $end
$var wire 8 # I [7:0] $end
$var reg 3 $ out [2:0] $end
$upscope $end
$upscope $end
$enddefinitions $end
$comment Show the parameter values. $end
$dumpall
$end
#0
$dumpvars
b0 $
b1 #
b1 "
b0 !
$end
#10
b1 !
b1 $
b11 "
b11 #
#20
b10 !
b10 $
b111 "
b111 #
#30
b11 !
b11 $
b1111 "
b1111 #
#40
b100 !
b100 $
b11111 "
b11111 #
#50
b101 !
b101 $
b111111 "
b111111 #
#60
b110 !
b110 $
b1111111 "
b1111111 #
#70
b111 !
b111 $
b11111111 "
b11111111 #
#80
b110 !
b110 $
b1011011 "
b1011011 #
#90
b111 !
b111 $
b11011011 "
b11011011 #
#100
b100 !
b100 $
b11011 "
b11011 #
#110
b11111 "
b11111 #
