sequential circuits/sequence detectors/mealyseqoverlap.v
//to detect sequence 0101 mealy overlapping
module mealyseqoverlap ( input clk,rst,x, output reg out);
parameter s0=2'b00 ,			//defining states
		s1=2'b01,
		s2=2'b10,
		s3=2'b11;
reg [1:0] state, next_state;

always @(posedge clk or negedge rst)
begin
if(~rst)
state<=s0;
else
state<=next_state;
end

always @(*)
begin
case(state)
s0 : begin
next_state=x?s0:s1;
end
s1 : begin
next_state=x?s2:s1;
end
s2 : begin
next_state=x?s0:s3;
end
s3 : begin
next_state=x?s2:s1;
end
default:next_state=s0;
endcase
end

always @(*)
begin
if(state==s3 && x==1)
out=1'b1;
else
out=1'b0;
end
endmodule

sequential circuits/sequence detectors/mealyseqoverlap_tb.v
module mealyseqoverlap_tb;
reg clk,rst,x;
wire out;
mealyseqoverlap DUT (.clk(clk),.rst(rst),.x(x),.out(out));
initial
clk=0;
always #2 clk=~clk;
initial
begin
x=0;
rst=0;#4;
rst=1;
x=0; #4;
x=1; #4;
x=0; #4;
x=1; #4;
x=0; #4;
x=1; #4;
x=0; #4;
x=1; #4;
x=0; #4;
x=1; #4;
x=0; #4;
x=1; #4;
#10;
$finish;
end
initial
begin
$dumpfile("mealyseqoverlap.vcd");
$dumpvars(0,mealyseqoverlap_tb);
end
endmodule

sequential circuits/sequence detectors/mealyseqoverlap.vcd
$date
	Thu Sep 25 23:18:06 2025
$end
$version
	Icarus Verilog
$end
$timescale
	1s
$end
$scope module mealyseqoverlap_tb $end
$var wire 1 ! out $end
$var reg 1 " clk $end
$var reg 1 # rst $end
$var reg 1 $ x $end
$scope module DUT $end
$var wire 1 " clk $end
$var wire 1 # rst $end
$var wire 1 $ x $end
$var parameter 2 % s0 $end
$var parameter 2 & s1 $end
$var parameter 2 ' s2 $end
$var parameter 2 ( s3 $end
$var reg 2 ) next_state [1:0] $end
$var reg 1 ! out $end
$var reg 2 * state [1:0] $end
$upscope $end
$upscope $end
$enddefinitions $end
$comment Show the parameter values. $end
$dumpall
b11 (
b10 '
b1 &
b0 %
$end
#0
$dumpvars
b0 *
b1 )
0$
0#
0"
0!
$end
#2
1"
#4
0"
1#
#6
b1 *
1"
#8
b10 )
0"
1$
#10
b0 )
b10 *
1"
#12
b11 )
0"
0$
#14
b1 )
b11 *
1"
#16
b10 )
1!
0"
1$
#18
0!
b0 )
b10 *
1"
#20
b11 )
0"
0$
#22
b1 )
b11 *
1"
#24
b10 )
1!
0"
1$
#26
0!
b0 )
b10 *
1"
#28
b11 )
0"
0$
#30
b1 )
b11 *
1"
#32
b10 )
1!
0"
1$
#34
0!
b0 )
b10 *
1"
#36
b11 )
0"
0$
#38
b1 )
b11 *
1"
#40
b10 )
1!
0"
1$
#42
0!
b0 )
b10 *
1"
#44
b11 )
0"
0$
#46
b1 )
b11 *
1"
#48
b10 )
1!
0"
1$
#50
0!
b0 )
b10 *
1"
#52
0"
#54
b0 *
1"
