sequential circuits/sequence detectors/mealyseqnonoverlap.v
//to detect 0101 - mealy non-overlapping
module mealyseqnonoverlap (input clk,rst,x, output reg out);
parameter s0=2'b00,s1=2'b01,s2=2'b10,s3=2'b11;
reg [1:0] state, next_state;
always @(posedge clk or negedge rst)
begin
if(~rst)
state<=s0;
else
state<=next_state;
end

always @(*)
begin
case(state)
s0: begin
next_state=(x==0)?s1:s0;
end
s1:begin
next_state=(x==1)?s2:s1;
end
s2:begin
next_state=(x==0)?s3:s0;
end
s3:begin
next_state=s0;
end
default: next_state=s0;
endcase
end

always @(*)
begin
if(state==s3 && x==1)
out=1'b1;
else
out=1'b0;
end
endmodule

sequential circuits/sequence detectors/mealyseqnonoverlap_tb.v
module mealyseqnonoverlap_tb;
reg clk,rst,x;
wire out;
mealyseqnonoverlap DUT(.clk(clk),.rst(rst),.x(x),.out(out));
initial
clk=0;
always #2 clk=~clk;
initial
begin
x=0;
rst=0;#4;
rst=1;
x=0; #4;
x=1; #4;
x=0; #4;
x=1; #4;
x=1; #4;
x=0; #4;
x=1; #4;   
x=0; #4;
x=1; #4;
#20;
$finish;
end
initial
begin
$dumpfile("mealyseqnonoverlap.vcd");
$dumpvars(0,mealyseqnonoverlap_tb);
end
endmodule

sequential circuits/sequence detectors/mealyseqnonoverlap.vcd
$date
	Thu Sep 25 17:39:49 2025
$end
$version
	Icarus Verilog
$end
$timescale
	1s
$end
$scope module mealyseqnonoverlap_tb $end
$var wire 1 ! out $end
$var reg 1 " clk $end
$var reg 1 # rst $end
$var reg 1 $ x $end
$scope module DUT $end
$var wire 1 " clk $end
$var wire 1 # rst $end
$var wire 1 $ x $end
$var parameter 2 % s0 $end
$var parameter 2 & s1 $end
$var parameter 2 ' s2 $end
$var parameter 2 ( s3 $end
$var reg 2 ) next_state [1:0] $end
$var reg 1 ! out $end
$var reg 2 * state [1:0] $end
$upscope $end
$upscope $end
$enddefinitions $end
$comment Show the parameter values. $end
$dumpall
b11 (
b10 '
b1 &
b0 %
$end
#0
$dumpvars
b0 *
b1 )
0$
0#
0"
0!
$end
#2
1"
#4
0"
1#
#6
b1 *
1"
#8
b10 )
0"
1$
#10
b0 )
b10 *
1"
#12
b11 )
0"
0$
#14
b0 )
b11 *
1"
#16
1!
0"
1$
#18
0!
b0 *
1"
#20
0"
#22
1"
#24
b1 )
0"
0$
#26
b1 *
1"
#28
b10 )
0"
1$
#30
b0 )
b10 *
1"
#32
b11 )
0"
0$
#34
b0 )
b11 *
1"
#36
1!
0"
1$
#38
0!
b0 *
1"
