Comb/21_MUX/mux21_struct.v
module mux21_struct(input i0,i1,s,output out);
wire w1,w2,w3;
not(w3,s);
and g1(w1,i0,w3);
and g2(w2.i1,s);
or(out,w1,w2);
endmodule

Comb/21_MUX/mux21_struct_tb.v
module mux21_struct_tb;
reg i0,i1;
reg s;
wire out;
mux21_struct DUT(i0,i1,s,out);
initial
begin
i0=0;
i1=1;
repeat(3)
begin
s=0;#10;
$display("s:%d\tout:%d",s, out);
s=1;#10;
$display("s:%d\tout:%d",s, out);
s=1;#10;
$display("s:%d\tout:%d",s, out);
s=0;#10;
$display("s:%d\tout:%d",s, out);
s=1;#10;
$display("s:%d\tout:%d",s, out);
end
end
initial
begin
$dumpfile("mux21.vcd");
$dumpvars(0,mux21_struct_tb);
end
endmodule

Comb/21_MUX/mux21.vcd
$date
	Thu Sep 18 21:00:15 2025
$end
$version
	Icarus Verilog
$end
$timescale
	1s
$end
$scope module mux21_struct_tb $end
$var wire 1 ! out $end
$var reg 1 " i0 $end
$var reg 1 # i1 $end
$var reg 1 $ s $end
$scope module DUT $end
$var wire 1 " i0 $end
$var wire 1 # i1 $end
$var wire 1 ! out $end
$var wire 1 $ s $end
$var wire 1 % w1 $end
$var wire 1 & w2 $end
$var wire 1 ' w3 $end
$upscope $end
$upscope $end
$enddefinitions $end
$comment Show the parameter values. $end
$dumpall
$end
#0
$dumpvars
1'
0&
0%
0$
1#
0"
0!
$end
#10
1!
0'
1&
1$
#30
0!
1'
0&
0$
#40
1!
0'
1&
1$
#50
0!
1'
0&
0$
#60
1!
0'
1&
1$
#80
0!
1'
0&
0$
#90
1!
0'
1&
1$
#100
0!
1'
0&
0$
#110
1!
0'
1&
1$
#130
0!
1'
0&
0$
#140
1!
0'
1&
1$
