Comb/full_adder/full_adder_ha.v
module half_add(input a,b,output sum,carry);
assign sum=a^b;
assign carry=a&b;
endmodule

module full_adder_ha(input a,b,cin,output sum,cout);
wire w1,w2,w3;
half_add ha1(a,b,w1,w2);
half_add ha2 (w1,cin,sum,w3);
or(cout,w2,w3);
endmodule

Comb/full_adder/full_adder_ha_tb.v
module full_adder_ha_tb;
reg a,b,cin;
wire sum,cout;
full_adder_ha DUT (a,b,cin,sum,cout);
initial
begin
a=0;b=0;cin=0;#10;
$display("a:%d,b:%d,cin:%d,sum:%d,cout:%d",a,b,cin,sum,cout);
a=0;b=0;cin=1;#10;
$display("a:%d,b:%d,cin:%d,sum:%d,cout:%d",a,b,cin,sum,cout);
a=0;b=1;cin=0;#10;
$display("a:%d,b:%d,cin:%d,sum:%d,cout:%d",a,b,cin,sum,cout);
a=0;b=1;cin=1;#10;
$display("a:%d,b:%d,cin:%d,sum:%d,cout:%d",a,b,cin,sum,cout);
a=1;b=0;cin=0;#10;
$display("a:%d,b:%d,cin:%d,sum:%d,cout:%d",a,b,cin,sum,cout);
a=1;b=0;cin=1;#10;
$display("a:%d,b:%d,cin:%d,sum:%d,cout:%d",a,b,cin,sum,cout);
a=1;b=1;cin=0;#10;
$display("a:%d,b:%d,cin:%d,sum:%d,cout:%d",a,b,cin,sum,cout);
a=1;b=1;cin=1;#10;
$display("a:%d,b:%d,cin:%d,sum:%d,cout:%d",a,b,cin,sum,cout);
end
initial 
begin
$dumpfile("full_adder.vcd");
$dumpvars(0,full_adder_ha_tb);
end
endmodule

Comb/full_adder/full_adder.vcd
$date
	Thu Sep 18 20:52:36 2025
$end
$version
	Icarus Verilog
$end
$timescale
	1s
$end
$scope module full_adder_ha_tb $end
$var wire 1 ! sum $end
$var wire 1 " cout $end
$var reg 1 # a $end
$var reg 1 $ b $end
$var reg 1 % cin $end
$scope module DUT $end
$var wire 1 # a $end
$var wire 1 $ b $end
$var wire 1 % cin $end
$var wire 1 " cout $end
$var wire 1 & w3 $end
$var wire 1 ' w2 $end
$var wire 1 ( w1 $end
$var wire 1 ! sum $end
$scope module ha1 $end
$var wire 1 # a $end
$var wire 1 $ b $end
$var wire 1 ' carry $end
$var wire 1 ( sum $end
$upscope $end
$scope module ha2 $end
$var wire 1 ( a $end
$var wire 1 % b $end
$var wire 1 & carry $end
$var wire 1 ! sum $end
$upscope $end
$upscope $end
$upscope $end
$enddefinitions $end
$comment Show the parameter values. $end
$dumpall
$end
#0
$dumpvars
0(
0'
0&
0%
0$
0#
0"
0!
$end
#10
1!
1%
#20
1(
0%
1$
#30
1"
0!
1&
1%
#40
0"
1!
0&
0%
0$
1#
#50
1"
0!
1&
1%
#60
0&
0(
1'
0%
1$
#70
1!
1%
