sequential circuits/latches/srlatch_nor.v
module srlatch_nor(input s,r,en,output reg q,output qb);
assign qb=~q;
always @(*)
begin
if(!en)
q<=0;
else
case({s,r})
2'b00 : q<=0;
2'b01 :q<=0;
2'b10 :q<=1;
2'b10:q<=1'bx;
default: q<=1'bx;
endcase
end
endmodule

sequential circuits/latches/srlatch_nor_tb.v
module srlatch_nor_tb;
reg s,r,en;
wire q,qb;
srlatch_nor  DUT(.s(s),.r(r),.en(en),.q(q),.qb(qb));
initial
begin
$monitor("time : %0t,en:%d,s:%d,r:%d,out:%d",$time,en,s,r,q);
en=0;#10;
en=1;
s=0;r=0;#10;
s=0;r=1;#10;
s=1;r=0;#10;
s=1;r=1;#10;
en=0;
s=1;r=0;#10;
s=1;r=1;#10;
en=1;
s=1;r=0;#10;
s=1;r=1;#10;
end
initial
begin
$dumpfile("srlatch_nor.vcd");
$dumpvars(0,srlatch_nor_tb);
end
endmodule

sequential circuits/latches/srlatch_nor.vcd
$date
	Sun Sep 21 20:44:18 2025
$end
$version
	Icarus Verilog
$end
$timescale
	1s
$end
$scope module srlatch_nor_tb $end
$var wire 1 ! qb $end
$var wire 1 " q $end
$var reg 1 # en $end
$var reg 1 $ r $end
$var reg 1 % s $end
$scope module DUT $end
$var wire 1 # en $end
$var wire 1 ! qb $end
$var wire 1 $ r $end
$var wire 1 % s $end
$var reg 1 " q $end
$upscope $end
$upscope $end
$enddefinitions $end
$comment Show the parameter values. $end
$dumpall
$end
#0
$dumpvars
x%
x$
0#
0"
1!
$end
#10
0$
0%
1#
#20
1$
#30
0!
1"
0$
1%
#40
x!
x"
1$
#50
1!
0"
0$
0#
#60
1$
#70
0!
1"
0$
1#
#80
x!
x"
1$
