Comb/decoder/decoder38.v
module decoder38 (input [2:0]A,output reg [7:0] out);
always @(*)
begin
case(A)
3'b000 : out=8'b10000000;
3'b001 : out=8'b01000000;
3'b010 : out=8'b00100000;
3'b011 : out=8'b00010000;
3'b100 : out=8'b00001000;
3'b101 : out=8'b00000100;
3'b110 : out=8'b00000010;
3'b111 : out=8'b00000001;
default:out=8'b00000000;
endcase
end
endmodule

Comb/decoder/decoder38_tb.v
module decoder38_tb;
reg [2:0]A;
wire [7:0] out;
decoder38 DUT(.A(A),.out(out));
initial
begin
A=3'b000;#10;
$display("Input is %d , output is %d",A,out);
A=3'b001;#10;
$display("Input is %d , output is %d",A,out);
A=3'b010;#10;
$display("Input is %d , output is %d",A,out);
A=3'b011;#10;
$display("Input is %d , output is %d",A,out);
A=3'b100;#10;
$display("Input is %d , output is %d",A,out);
A=3'b101;#10;
$display("Input is %d , output is %d",A,out);
A=3'b110;#10;
$display("Input is %d , output is %d",A,out);
A=3'b111;#10;
$display("Input is %d , output is %d",A,out);
end
initial
begin
$dumpfile("decoder38.vcd");
$dumpvars(0,decoder38_tb);
end
endmodule

Comb/decoder/decoder38.vcd
$date
	Sun Sep 21 19:33:05 2025
$end
$version
	Icarus Verilog
$end
$timescale
	1s
$end
$scope module decoder38_tb $end
$var wire 8 ! out [7:0] $end
$var reg 3 " A [2:0] $end
$scope module DUT $end
$var wire 3 # A [2:0] $end
$var reg 8 $ out [7:0] $end
$upscope $end
$upscope $end
$enddefinitions $end
$comment Show the parameter values. $end
$dumpall
$end
#0
$dumpvars
b10000000 $
b0 #
b0 "
b10000000 !
$end
#10
b1000000 !
b1000000 $
b1 "
b1 #
#20
b100000 !
b100000 $
b10 "
b10 #
#30
b10000 !
b10000 $
b11 "
b11 #
#40
b1000 !
b1000 $
b100 "
b100 #
#50
b100 !
b100 $
b101 "
b101 #
#60
b10 !
b10 $
b110 "
b110 #
#70
b1 !
b1 $
b111 "
b111 #
