Comb/81_mux/mux81.v
module mux41_cond(input [3:0]I,
input [1:0]S,output out);
assign out=S[1]?(S[0]?I[3]:I[2]):(S[0]?I[1]:I[0]);
endmodule

module mux21(input [1:0]i, input s, output out);
assign out=s?i[1]:i[0]; //using conditional operator
endmodule

module mux81(input [7:0]I,
             input [2:0]S,
             output out);
wire w1, w2;

mux41_cond m1 (.I(I[3:0]), .S(S[1:0]), .out(w1));
mux41_cond m2 (.I(I[7:4]), .S(S[1:0]), .out(w2));
mux21      m3 (.i({w2, w1}), .s(S[2]), .out(out));

endmodule

Comb/81_mux/mux81_tb.v
module mux81_tb;
reg [7:0]I;
reg [2:0] S;
wire out;
mux81 DUT(I,S,out);
initial
begin
I=8'b11101010;
S=3'b000;#10;
$display("S2:%d,S1:%d,S0:%d,out:%d",S[2],S[1],S[0],out);
S=3'b001;#10;
$display("S2:%d,S1:%d,S0:%d,out:%d",S[2],S[1],S[0],out);
S=3'b010;#10;
$display("S2:%d,S1:%d,S0:%d,out:%d",S[2],S[1],S[0],out);
S=3'b011;#10;
$display("S2:%d,S1:%d,S0:%d,out:%d",S[2],S[1],S[0],out);
S=3'b100;#10;
$display("S2:%d,S1:%d,S0:%d,out:%d",S[2],S[1],S[0],out);
S=3'b101;#10;
$display("S2:%d,S1:%d,S0:%d,out:%d",S[2],S[1],S[0],out);
S=3'b110;#10;
$display("S2:%d,S1:%d,S0:%d,out:%d",S[2],S[1],S[0],out);
S=3'b111;#10;
$display("S2:%d,S1:%d,S0:%d,out:%d",S[2],S[1],S[0],out);
end
initial
begin
$dumpfile("mux81.vcd");
$dumpvars(0,mux81_tb);
end
endmodule

Comb/81_mux/mux81.vcd
$date
	Thu Sep 18 22:16:42 2025
$end
$version
	Icarus Verilog
$end
$timescale
	1s
$end
$scope module mux81_tb $end
$var wire 1 ! out $end
$var reg 8 " I [7:0] $end
$var reg 3 # S [2:0] $end
$scope module DUT $end
$var wire 8 $ I [7:0] $end
$var wire 3 % S [2:0] $end
$var wire 1 & w2 $end
$var wire 1 ' w1 $end
$var wire 1 ! out $end
$scope module m1 $end
$var wire 4 ( I [3:0] $end
$var wire 2 ) S [1:0] $end
$var wire 1 ' out $end
$upscope $end
$scope module m2 $end
$var wire 4 * I [3:0] $end
$var wire 2 + S [1:0] $end
$var wire 1 & out $end
$upscope $end
$scope module m3 $end
$var wire 2 , i [1:0] $end
$var wire 1 - s $end
$var wire 1 ! out $end
$upscope $end
$upscope $end
$upscope $end
$enddefinitions $end
$comment Show the parameter values. $end
$dumpall
$end
#0
$dumpvars
0-
b0 ,
b0 +
b1110 *
b0 )
b1010 (
0'
0&
b0 %
b11101010 $
b0 #
b11101010 "
0!
$end
#10
1!
1'
b11 ,
1&
b1 )
b1 +
b1 #
b1 %
#20
0!
b10 ,
0'
b10 )
b10 +
b10 #
b10 %
#30
1!
b11 ,
1'
b11 )
b11 +
b11 #
b11 %
#40
0!
0'
b0 ,
0&
b0 )
b0 +
1-
b100 #
b100 %
#50
1!
1'
b11 ,
1&
b1 )
b1 +
b101 #
b101 %
#60
b10 ,
0'
b10 )
b10 +
b110 #
b110 %
#70
b11 ,
1'
b11 )
b11 +
b111 #
b111 %
